flipperzero/__init__.py
flipperzero-1.5.0.dist-info/METADATA
flipperzero-1.5.0.dist-info/WHEEL
flipperzero-1.5.0.dist-info/licenses/LICENSE.txt
flipperzero-1.5.0.dist-info/RECORD
